jzon/__init__.py
jzon/jzon.py
jzon-0.1.0.dist-info/LICENSE
jzon-0.1.0.dist-info/METADATA
jzon-0.1.0.dist-info/WHEEL
jzon-0.1.0.dist-info/top_level.txt
jzon-0.1.0.dist-info/RECORD
