Metadata-Version: 2.1
Name: jzon
Version: 0.1.0
Summary: A simple library to convert dictionaries to JSON files.
Home-page: https://github.com/Jjioo/jzon
Author: Tarek Ziad
Author-email: heroesofdawn.18@gmail.com
License: MIT
Classifier: Programming Language :: Python :: 3
Classifier: License :: OSI Approved :: MIT License
Classifier: Operating System :: OS Independent
Requires-Python: >=3.6
License-File: LICENSE
